main/__init__.py
main/main.py
main/test.py
main/controller/Controller.py
main/controller/__init__.py
main/models/__init__.py
main/models/airflow/__init__.py
main/models/airflow/airflow_client.py
main/models/conn_validator/__init__.py
main/models/conn_validator/conn_validator.py
main/models/dag_builder/__init__.py
main/models/dag_builder/dag_builder.py
main/models/project/__init__.py
main/models/project/project.py
main/models/schema_creator/__init__.py
main/models/schema_creator/schema_creator.py
main/models/schema_validator/__init__.py
main/models/schema_validator/schema_validator.py
qmt_data-0.1.0.dist-info/METADATA
qmt_data-0.1.0.dist-info/WHEEL
qmt_data-0.1.0.dist-info/entry_points.txt
qmt_data-0.1.0.dist-info/top_level.txt
qmt_data-0.1.0.dist-info/RECORD
