Metadata-Version: 2.4
Name: qmt-data
Version: 0.1.0
Summary: QMT – Airflow DAG Generator CLI
Author: Твоє Імʼя
Author-email: email@example.com
Classifier: Programming Language :: Python :: 3
Classifier: Operating System :: OS Independent
Requires-Python: >=3.7
Dynamic: author
Dynamic: author-email
Dynamic: classifier
Dynamic: requires-python
Dynamic: summary
